cognite_kuiper-0.18.0.dist-info/METADATA
cognite_kuiper-0.18.0.dist-info/WHEEL
kuiper/__init__.py
kuiper/kuiper.cpython-310-darwin.so
kuiper/kuiper.pyi
kuiper/py.typed
cognite_kuiper-0.18.0.dist-info/RECORD
