Metadata-Version: 2.4
Name: cognite-kuiper
Version: 0.18.0
Classifier: Development Status :: 4 - Beta
Classifier: Programming Language :: Rust
Classifier: Programming Language :: Python
Requires-Dist: pytest ; extra == 'test'
Provides-Extra: test
Summary: A JSON to JSON transform and templating language from Cognite
Keywords: JSON,transformation
Author-email: Mathias Lohne <mathias.lohne@cognite.com>
Maintainer-email: Mathias Lohne <mathias.lohne@cognite.com>
License: Apache-2.0
Requires-Python: >=3.10
Project-URL: homepage, https://cognite.com
Project-URL: repository, https://github.com/cognitedata/kuiper
